httpx_html.py
httpx_html-0.11.0.dev0.dist-info/LICENSE
httpx_html-0.11.0.dev0.dist-info/METADATA
httpx_html-0.11.0.dev0.dist-info/WHEEL
httpx_html-0.11.0.dev0.dist-info/top_level.txt
httpx_html-0.11.0.dev0.dist-info/RECORD
