Metadata-Version: 2.1
Name: httpx-html
Version: 0.11.0.dev0
Summary: Web Scraping for Humans.
Home-page: https://github.com/nuno-andre/httpx-html
Author: Kenneth Reitz
Author-email: me@kennethreitz.org
Maintainer: Nuno André
Maintainer-email: mail@nunoand.re
License: MIT
Project-URL: Source, https://github.com/nuno-andre/httpx-html
Project-URL: Bug Tracker, https://github.com/nuno-andre/httpx-html/issues
Platform: any
Classifier: License :: OSI Approved :: MIT License
Classifier: Operating System :: OS Independent
Classifier: Programming Language :: Python
Classifier: Programming Language :: Python :: 3.6
Classifier: Programming Language :: Python :: 3.7
Classifier: Programming Language :: Python :: 3.8
Classifier: Programming Language :: Python :: 3.9
Classifier: Programming Language :: Python :: Implementation :: CPython
Classifier: Programming Language :: Python :: Implementation :: PyPy
Classifier: Typing :: Typed
Requires-Python: >=3.6.0
Provides-Extra: tests
Provides-Extra: docs
Provides-Extra: dev
License-File: LICENSE
